[
  {
    "event": "SERIE A: Verona vs Genoa",
    "start": "23:49",
    "end": "01:49",
    "url": "https://m-3-u-player--hermixervdj94.replit.app/?channel=espn"
  },
  {
    "event": "LA LIGA: Atletico Madrid vs Villarreal",
    "start": "01:49",
    "end": "02:43",
    "url": "https://m-3-u-player--hermixervdj94.replit.app/?channel=espn2"
  },
  {
    "event": "PREMIER LEAGUE: Chelsea vs Arsenal",
    "start": "04:30",
    "end": "07:00",
    "url": "https://m-3-u-player--hermixervdj94.replit.app/?channel=fox1ar"
  }
]
